[
  {
    "id": 1,
    "nama": "Djimat Coffee",
    "nuansa": "Klasik Jawa",
    "deskripsi": "Kafe dengan interior penuh koleksi antik dan memorabilia Solo. Dekorasi wayang, batik, dan perabot kayu jati tua menciptakan suasana nostalgia.",
    "alamat": "Jl. Gatot Subroto, Solo",
    "jam_buka": "09.00 - 22.00 WIB",
    "harga_rata": "Rp 25.000 - 50.000",
    "wifi": true,
    "rating": 4.6,
    "foto": "",
    "menu_andalan": "Kopi Joss, Wedang Uwuh"
  },
  {
    "id": 2,
    "nama": "Njimat Kopi",
    "nuansa": "Heritage",
    "deskripsi": "Bangunan bersejarah yang disulap menjadi kafe estetik. Perpaduan arsitektur kolonial dengan sentuhan modern. Spot foto favorit.",
    "alamat": "Kawasan Laweyan, Solo",
    "jam_buka": "10.00 - 21.00 WIB",
    "harga_rata": "Rp 30.000 - 60.000",
    "wifi": true,
    "rating": 4.7,
    "foto": "",
    "menu_andalan": "Single Origin Arabica, Kopi Tubruk"
  },
  {
    "id": 3,
    "nama": "Yellow Truck Coffee",
    "nuansa": "Modern",
    "deskripsi": "Kafe specialty coffee modern dengan barista berpengalaman. Berbagai metode seduh: V60, Chemex, AeroPress, dan espresso base.",
    "alamat": "Jl. Slamet Riyadi, Solo",
    "jam_buka": "08.00 - 22.00 WIB",
    "harga_rata": "Rp 30.000 - 65.000",
    "wifi": true,
    "rating": 4.5,
    "foto": "",
    "menu_andalan": "V60 Single Origin, Signature Latte"
  },
  {
    "id": 4,
    "nama": "Warung Kopi Bong",
    "nuansa": "Tradisional",
    "deskripsi": "Warung kopi legendaris Solo yang sudah berdiri puluhan tahun. Kopi robusta tubruk asli dengan harga sangat terjangkau. Langganan warga lokal.",
    "alamat": "Pasar Gede, Solo",
    "jam_buka": "06.00 - 12.00 WIB",
    "harga_rata": "Rp 5.000 - 15.000",
    "wifi": false,
    "rating": 4.4,
    "foto": "",
    "menu_andalan": "Kopi Tubruk, Teh Poci"
  },
  {
    "id": 5,
    "nama": "Story Coffee",
    "nuansa": "Instagramable",
    "deskripsi": "Kafe dengan desain interior estetik bergaya industrial-vintage. Banyak spot foto menarik dengan pencahayaan yang sempurna untuk konten.",
    "alamat": "Jl. Yosodipuro, Banjarsari, Solo",
    "jam_buka": "10.00 - 23.00 WIB",
    "harga_rata": "Rp 35.000 - 70.000",
    "wifi": true,
    "rating": 4.5,
    "foto": "",
    "menu_andalan": "Salted Caramel Latte, Brown Sugar Boba"
  },
  {
    "id": 6,
    "nama": "Omah Sinten Heritage Hotel Cafe",
    "nuansa": "Heritage",
    "deskripsi": "Kafe dalam bangunan cagar budaya abad ke-19. Suasana tempo dulu yang autentik dengan taman dalam yang asri. Pengalaman ngopi yang tak terlupakan.",
    "alamat": "Jl. Diponegoro No.44, Timuran, Banjarsari, Solo",
    "jam_buka": "07.00 - 22.00 WIB",
    "harga_rata": "Rp 40.000 - 80.000",
    "wifi": true,
    "rating": 4.8,
    "foto": "",
    "menu_andalan": "Kopi Keraton, Teh Melati"
  }
]
